{"AC": {"en": {"percent": 99.0, "official": "False"}}, "AD": {"ca": {"percent": 51.0, "official": "True"}, "es": {"percent": 43.0, "official": "False"}, "fr": {"percent": 7.5, "official": "False"}}, "AE": {"ar": {"percent": 78.0, "official": "True"}, "en": {"percent": 50.0, "official": "False"}, "ml": {"percent": 7.0, "official": "False"}, "ps": {"percent": 2.9, "official": "False"}, "bal": {"percent": 2.3, "official": "False"}, "fa": {"percent": 1.9, "official": "False"}}, "AF": {"fa": {"percent": 50.0, "official": "True"}, "ps": {"percent": 43.0, "official": "True"}, "haz": {"percent": 5.9, "official": "False"}, "uz_Arab": {"percent": 4.7, "official": "True"}, "tk": {"percent": 1.7, "official": "True"}, "prd": {"percent": 1.2, "official": "False"}, "bgn": {"percent": 0.63, "official": "False"}, "ug": {"percent": 0.0082, "official": "False"}, "kk_Arab": {"percent": 0.0055, "official": "False"}}, "AG": {"en": {"percent": 86.0, "official": "True"}, "pt": {"percent": 1.6, "official": "False"}}, "AI": {"en": {"percent": 95.0, "official": "True"}}, "AL": {"sq": {"percent": 100.0, "official": "True"}, "el": {"percent": 1.9, "official": "False"}, "mk": {"percent": 0.47, "official": "False"}}, "AM": {"hy": {"percent": 98.0, "official": "True"}, "ku": {"percent": 3.3, "official": "False"}, "az": {"percent": 0.0, "official": "False"}}, "AO": {"pt": {"percent": 67.0, "official": "True"}, "umb": {"percent": 29.0, "official": "False"}, "kmb": {"percent": 25.0, "official": "False"}, "ln": {"percent": 0.67, "official": "False"}}, "AQ": {"und": {"percent": 100.0, "official": "False"}}, "AR": {"es": {"percent": 100.0, "official": "True"}, "en": {"percent": 7.0, "official": "False"}, "cy": {"percent": 0.066, "official": "False"}, "gn": {"percent": 0.047, "official": "False"}}, "AS": {"sm": {"percent": 99.0, "official": "True"}, "en": {"percent": 97.0, "official": "True"}}, "AT": {"de": {"percent": 97.0, "official": "True"}, "bar": {"percent": 95.0, "official": "False"}, "en": {"percent": 73.0, "official": "False"}, "fr": {"percent": 11.0, "official": "False"}, "it": {"percent": 9.0, "official": "False"}, "hr": {"percent": 1.2, "official": "True"}, "sl": {"percent": 0.37, "official": "True"}, "hu": {"percent": 0.26, "official": "True"}}, "AU": {"en": {"percent": 96.0, "official": "True"}, "zh_Hant": {"percent": 2.1, "official": "False"}, "it": {"percent": 1.9, "official": "False"}, "wbp": {"percent": 0.0098, "official": "False"}}, "AW": {"nl": {"percent": 97.0, "official": "True"}, "pap": {"percent": 61.0, "official": "True"}, "en": {"percent": 2.5, "official": "False"}}, "AX": {"sv": {"percent": 99.0, "official": "True"}}, "AZ": {"az": {"percent": 89.0, "official": "True"}, "az_Cyrl": {"percent": 9.9, "official": "True"}, "tly": {"percent": 9.8, "official": "False"}, "ku": {"percent": 0.24, "official": "False"}, "ttt": {"percent": 0.22, "official": "False"}, "tkr": {"percent": 0.16, "official": "False"}}, "BA": {"bs": {"percent": 99.0, "official": "True"}, "bs_Cyrl": {"percent": 99.0, "official": "True"}, "en": {"percent": 45.0, "official": "False"}, "hr": {"percent": 12.0, "official": "True"}, "sr": {"percent": 10.0, "official": "True"}, "sr_Latn": {"percent": 10.0, "official": "True"}}, "BB": {"en": {"percent": 100.0, "official": "True"}}, "BD": {"bn": {"percent": 98.0, "official": "True"}, "en": {"percent": 18.0, "official": "False"}, "rkt": {"percent": 6.5, "official": "False"}, "syl": {"percent": 5.0, "official": "False"}, "rhg": {"percent": 0.53, "official": "False"}, "ccp": {"percent": 0.22, "official": "False"}, "my": {"percent": 0.21, "official": "False"}, "grt": {"percent": 0.073, "official": "False"}, "mro": {"percent": 0.018, "official": "False"}, "mni": {"percent": 0.011, "official": "False"}}, "BE": {"en": {"percent": 59.0, "official": "False"}, "nl": {"percent": 55.0, "official": "True"}, "fr": {"percent": 38.0, "official": "True"}, "de": {"percent": 22.0, "official": "True"}, "vls": {"percent": 10.0, "official": "False"}, "wa": {"percent": 5.8, "official": "False"}}, "BF": {"mos": {"percent": 40.0, "official": "False"}, "dyu": {"percent": 32.0, "official": "False"}, "fr": {"percent": 22.0, "official": "True"}, "ff": {"percent": 0.0, "official": "False"}, "ff_Adlm": {"percent": 0.0, "official": "False"}}, "BG": {"bg": {"percent": 100.0, "official": "True"}, "en": {"percent": 25.0, "official": "False"}, "ru": {"percent": 23.0, "official": "False"}, "tr": {"percent": 11.0, "official": "False"}, "de": {"percent": 8.0, "official": "False"}}, "BH": {"ar": {"percent": 87.0, "official": "True"}, "ml": {"percent": 3.3, "official": "False"}}, "BI": {"rn": {"percent": 63.0, "official": "True"}, "fr": {"percent": 59.0, "official": "True"}, "sw": {"percent": 0.054, "official": "False"}, "en": {"percent": 0.053, "official": "True"}}, "BJ": {"fr": {"percent": 35.0, "official": "True"}, "fon": {"percent": 25.0, "official": "False"}, "yo": {"percent": 6.7, "official": "False"}}, "BL": {"fr": {"percent": 96.0, "official": "True"}}, "BM": {"en": {"percent": 92.0, "official": "True"}}, "BN": {"ms": {"percent": 93.0, "official": "True"}, "zh_Hant": {"percent": 11.0, "official": "False"}, "ms_Arab": {"percent": 5.0, "official": "True"}, "en": {"percent": 1.7, "official": "False"}}, "BO": {"es": {"percent": 61.0, "official": "True"}, "qu": {"percent": 32.0, "official": "True"}, "ay": {"percent": 20.0, "official": "True"}, "gn": {"percent": 0.45, "official": "False"}, "aro": {"percent": 0.0009, "official": "False"}}, "BQ": {"pap": {"percent": 81.0, "official": "False"}, "nl": {"percent": 8.0, "official": "True"}}, "BR": {"pt": {"percent": 91.0, "official": "True"}, "en": {"percent": 8.0, "official": "False"}, "de": {"percent": 0.84, "official": "False"}, "it": {"percent": 0.28, "official": "False"}, "ja": {"percent": 0.21, "official": "False"}, "es": {"percent": 0.036, "official": "False"}, "kgp": {"percent": 0.024, "official": "False"}, "ko": {"percent": 0.021, "official": "False"}, "yrl": {"percent": 0.01, "official": "False"}, "gub": {"percent": 0.0084, "official": "False"}, "xav": {"percent": 0.0047, "official": "False"}}, "BS": {"en": {"percent": 100.0, "official": "True"}}, "BT": {"dz": {"percent": 47.0, "official": "True"}, "ne": {"percent": 17.0, "official": "False"}, "tsj": {"percent": 15.0, "official": "False"}, "en": {"percent": 11.0, "official": "False"}, "lep": {"percent": 3.9, "official": "False"}}, "BV": {"und": {"percent": 100.0, "official": "False"}}, "BW": {"en": {"percent": 81.0, "official": "True"}, "tn": {"percent": 62.0, "official": "True"}, "af": {"percent": 0.26, "official": "False"}}, "BY": {"be": {"percent": 100.0, "official": "True"}, "ru": {"percent": 12.0, "official": "True"}}, "BZ": {"en": {"percent": 100.0, "official": "True"}, "es": {"percent": 28.0, "official": "False"}}, "CA": {"en": {"percent": 86.0, "official": "True"}, "fr": {"percent": 22.0, "official": "True"}, "it": {"percent": 2.0, "official": "False"}, "de": {"percent": 1.9, "official": "False"}, "pdt": {"percent": 0.24, "official": "False"}, "cr": {"percent": 0.11, "official": "False"}, "crk": {"percent": 0.11, "official": "False"}, "yi": {"percent": 0.045, "official": "False"}, "iu": {"percent": 0.042, "official": "True"}, "iu_Latn": {"percent": 0.042, "official": "True"}, "moe": {"percent": 0.033, "official": "False"}, "crj": {"percent": 0.019, "official": "False"}, "atj": {"percent": 0.015, "official": "False"}, "crl": {"percent": 0.014, "official": "False"}, "csw": {"percent": 0.013, "official": "False"}, "crm": {"percent": 0.012, "official": "False"}, "ikt": {"percent": 0.011, "official": "True"}, "moh": {"percent": 0.0093, "official": "False"}, "dgr": {"percent": 0.007, "official": "False"}, "den": {"percent": 0.0061, "official": "False"}, "scs": {"percent": 0.0033, "official": "False"}, "nsk": {"percent": 0.0031, "official": "False"}, "chp": {"percent": 0.002, "official": "False"}, "gwi": {"percent": 0.0015, "official": "False"}}, "CC": {"ms_Arab": {"percent": 83.0, "official": "False"}, "en": {"percent": 17.0, "official": "True"}}, "CD": {"sw": {"percent": 50.0, "official": "True"}, "lua": {"percent": 9.6, "official": "True"}, "fr": {"percent": 3.8, "official": "True"}, "ln": {"percent": 3.1, "official": "True"}, "lu": {"percent": 2.3, "official": "False"}, "kg": {"percent": 1.5, "official": "True"}, "lol": {"percent": 0.61, "official": "False"}, "rw": {"percent": 0.38, "official": "False"}}, "CF": {"fr": {"percent": 49.0, "official": "True"}, "sg": {"percent": 49.0, "official": "True"}, "ln": {"percent": 0.24, "official": "False"}}, "CG": {"fr": {"percent": 84.0, "official": "True"}, "ln": {"percent": 2.4, "official": "False"}}, "CH": {"de": {"percent": 73.0, "official": "True"}, "gsw": {"percent": 65.0, "official": "True"}, "en": {"percent": 61.0, "official": "False"}, "fr": {"percent": 21.0, "official": "True"}, "it": {"percent": 4.3, "official": "True"}, "lmo": {"percent": 4.1, "official": "False"}, "pt": {"percent": 3.4, "official": "False"}, "rm": {"percent": 0.5, "official": "True"}, "rmo": {"percent": 0.29, "official": "False"}, "wae": {"percent": 0.12, "official": "False"}}, "CI": {"fr": {"percent": 49.0, "official": "True"}, "bci": {"percent": 11.0, "official": "False"}, "sef": {"percent": 4.3, "official": "False"}, "dnj": {"percent": 4.0, "official": "False"}, "kfo": {"percent": 0.23, "official": "False"}, "bqv": {"percent": 0.17, "official": "False"}}, "CK": {"en": {"percent": 100.0, "official": "True"}}, "CL": {"es": {"percent": 98.0, "official": "True"}, "en": {"percent": 9.5, "official": "False"}, "arn": {"percent": 1.5, "official": "False"}}, "CM": {"fr": {"percent": 68.0, "official": "True"}, "en": {"percent": 38.0, "official": "True"}, "bum": {"percent": 4.6, "official": "False"}, "ff": {"percent": 3.6, "official": "False"}, "ewo": {"percent": 3.1, "official": "False"}, "ybb": {"percent": 1.6, "official": "False"}, "bbj": {"percent": 1.4, "official": "False"}, "nnh": {"percent": 1.4, "official": "False"}, "bkm": {"percent": 1.3, "official": "False"}, "bas": {"percent": 1.2, "official": "False"}, "bax": {"percent": 1.2, "official": "False"}, "byv": {"percent": 1.1, "official": "False"}, "mua": {"percent": 1.0, "official": "False"}, "maf": {"percent": 0.74, "official": "False"}, "bfd": {"percent": 0.57, "official": "False"}, "bss": {"percent": 0.54, "official": "False"}, "kkj": {"percent": 0.54, "official": "False"}, "dua": {"percent": 0.48, "official": "False"}, "mgo": {"percent": 0.47, "official": "False"}, "ar": {"percent": 0.39, "official": "False"}, "jgo": {"percent": 0.34, "official": "False"}, "ksf": {"percent": 0.32, "official": "False"}, "agq": {"percent": 0.14, "official": "False"}, "ha_Arab": {"percent": 0.14, "official": "False"}, "nmg": {"percent": 0.032, "official": "False"}, "yav": {"percent": 0.0083, "official": "False"}, "ff_Adlm": {"percent": 0.0, "official": "False"}}, "CN": {"zh": {"percent": 90.0, "official": "True"}, "wuu": {"percent": 6.0, "official": "False"}, "yue_Hans": {"percent": 5.2, "official": "False"}, "hsn": {"percent": 2.9, "official": "False"}, "hak": {"percent": 2.3, "official": "False"}, "nan": {"percent": 1.9, "official": "False"}, "gan": {"percent": 1.7, "official": "False"}, "ii": {"percent": 0.6, "official": "False"}, "ug": {"percent": 0.55, "official": "True"}, "za": {"percent": 0.31, "official": "True"}, "mn_Mong": {"percent": 0.26, "official": "True"}, "bo": {"percent": 0.2, "official": "True"}, "ko": {"percent": 0.15, "official": "True"}, "kk_Arab": {"percent": 0.085, "official": "False"}, "lis": {"percent": 0.045, "official": "False"}, "ky_Arab": {"percent": 0.034, "official": "False"}, "nxq": {"percent": 0.024, "official": "False"}, "khb": {"percent": 0.019, "official": "False"}, "tdd": {"percent": 0.019, "official": "False"}, "lcp": {"percent": 0.0058, "official": "False"}, "en": {"percent": 0.0045, "official": "False"}, "ru": {"percent": 0.001, "official": "False"}, "vi": {"percent": 0.0005, "official": "False"}, "uz_Cyrl": {"percent": 0.0004, "official": "False"}, "lzh": {"percent": 0.0, "official": "False"}}, "CO": {"es": {"percent": 93.0, "official": "True"}, "guc": {"percent": 0.27, "official": "False"}, "yrl": {"percent": 0.0061, "official": "False"}}, "CP": {"und": {"percent": 100.0, "official": "False"}}, "CR": {"es": {"percent": 95.0, "official": "True"}}, "CU": {"es": {"percent": 100.0, "official": "True"}}, "CV": {"kea": {"percent": 91.0, "official": "False"}, "pt": {"percent": 76.0, "official": "True"}}, "CW": {"pap": {"percent": 81.0, "official": "True"}, "nl": {"percent": 8.0, "official": "True"}, "es": {"percent": 3.8, "official": "False"}}, "CX": {"en": {"percent": 63.0, "official": "True"}}, "CY": {"el": {"percent": 95.0, "official": "True"}, "en": {"percent": 73.0, "official": "False"}, "tr": {"percent": 23.0, "official": "True"}, "fr": {"percent": 7.0, "official": "False"}, "hy": {"percent": 0.22, "official": "False"}, "ar": {"percent": 0.1, "official": "False"}}, "CZ": {"cs": {"percent": 98.0, "official": "True"}, "en": {"percent": 27.0, "official": "False"}, "sk": {"percent": 16.0, "official": "False"}, "de": {"percent": 15.0, "official": "False"}, "pl": {"percent": 0.49, "official": "False"}}, "DE": {"de": {"percent": 91.0, "official": "True"}, "en": {"percent": 64.0, "official": "False"}, "fr": {"percent": 18.0, "official": "False"}, "bar": {"percent": 17.0, "official": "False"}, "nds": {"percent": 12.0, "official": "False"}, "nl": {"percent": 9.0, "official": "False"}, "it": {"percent": 7.0, "official": "False"}, "es": {"percent": 6.0, "official": "False"}, "ru": {"percent": 6.0, "official": "False"}, "vmf": {"percent": 6.0, "official": "False"}, "tr": {"percent": 2.5, "official": "False"}, "gsw": {"percent": 2.3, "official": "False"}, "da": {"percent": 2.0, "official": "False"}, "swg": {"percent": 1.0, "official": "False"}, "hr": {"percent": 0.79, "official": "False"}, "ku": {"percent": 0.66, "official": "False"}, "el": {"percent": 0.38, "official": "False"}, "ksh": {"percent": 0.3, "official": "False"}, "pl": {"percent": 0.29, "official": "False"}, "hsb": {"percent": 0.016, "official": "False"}, "frr": {"percent": 0.012, "official": "False"}, "dsb": {"percent": 0.0087, "official": "False"}, "frs": {"percent": 0.0025, "official": "False"}, "stq": {"percent": 0.0012, "official": "False"}, "pfl": {"percent": 0.0, "official": "False"}}, "DG": {"en": {"percent": 99.0, "official": "True"}}, "DJ": {"aa": {"percent": 42.0, "official": "False"}, "so": {"percent": 41.0, "official": "False"}, "ar": {"percent": 7.3, "official": "True"}, "fr": {"percent": 2.1, "official": "True"}}, "DK": {"da": {"percent": 93.0, "official": "True"}, "en": {"percent": 86.0, "official": "False"}, "de": {"percent": 47.0, "official": "True"}, "sv": {"percent": 13.0, "official": "False"}, "fo": {"percent": 0.38, "official": "False"}, "kl": {"percent": 0.12, "official": "True"}, "jut": {"percent": 0.0, "official": "False"}}, "DM": {"en": {"percent": 94.0, "official": "True"}}, "DO": {"es": {"percent": 78.0, "official": "True"}, "en": {"percent": 0.076, "official": "False"}}, "DZ": {"arq": {"percent": 83.0, "official": "False"}, "ar": {"percent": 74.0, "official": "True"}, "fr": {"percent": 20.0, "official": "True"}, "kab": {"percent": 7.8, "official": "False"}, "en": {"percent": 7.0, "official": "False"}}, "EA": {"es": {"percent": 98.0, "official": "True"}}, "EC": {"es": {"percent": 96.0, "official": "True"}, "qu": {"percent": 17.0, "official": "True"}, "qug": {"percent": 5.7, "official": "False"}}, "EE": {"et": {"percent": 71.0, "official": "True"}, "ru": {"percent": 56.0, "official": "False"}, "en": {"percent": 50.0, "official": "False"}, "fi": {"percent": 21.0, "official": "False"}, "vro": {"percent": 5.7, "official": "False"}}, "EG": {"ar": {"percent": 94.0, "official": "True"}, "arz": {"percent": 64.0, "official": "False"}, "en": {"percent": 35.0, "official": "False"}, "el": {"percent": 0.061, "official": "False"}}, "EH": {"ar": {"percent": 100.0, "official": "True"}}, "ER": {"ti": {"percent": 60.0, "official": "True"}, "en": {"percent": 59.0, "official": "True"}, "tig": {"percent": 18.0, "official": "False"}, "ar": {"percent": 4.9, "official": "True"}, "aa": {"percent": 3.6, "official": "False"}, "ssy": {"percent": 3.6, "official": "False"}, "byn": {"percent": 1.3, "official": "False"}}, "ES": {"es": {"percent": 99.0, "official": "True"}, "en": {"percent": 24.0, "official": "False"}, "ca": {"percent": 17.0, "official": "True"}, "gl": {"percent": 7.0, "official": "True"}, "eu": {"percent": 2.0, "official": "True"}, "ast": {"percent": 1.3, "official": "True"}, "ext": {"percent": 0.49, "official": "False"}, "an": {"percent": 0.052, "official": "False"}}, "ET": {"en": {"percent": 43.0, "official": "False"}, "am": {"percent": 33.0, "official": "True"}, "om": {"percent": 32.0, "official": "False"}, "so": {"percent": 6.0, "official": "False"}, "ti": {"percent": 6.0, "official": "False"}, "sid": {"percent": 3.5, "official": "False"}, "wal": {"percent": 1.8, "official": "False"}, "aa": {"percent": 1.4, "official": "False"}}, "FI": {"fi": {"percent": 94.0, "official": "True"}, "en": {"percent": 70.0, "official": "False"}, "sv": {"percent": 44.0, "official": "True"}, "de": {"percent": 18.0, "official": "False"}, "ru": {"percent": 0.81, "official": "False"}, "et": {"percent": 0.11, "official": "False"}, "rmf": {"percent": 0.09, "official": "False"}, "se": {"percent": 0.036, "official": "False"}, "smn": {"percent": 0.011, "official": "False"}, "sms": {"percent": 0.011, "official": "False"}}, "FJ": {"en": {"percent": 94.0, "official": "True"}, "hi": {"percent": 44.0, "official": "False"}, "hif": {"percent": 41.0, "official": "True"}, "fj": {"percent": 39.0, "official": "True"}, "rtm": {"percent": 0.27, "official": "False"}}, "FK": {"en": {"percent": 88.0, "official": "True"}}, "FM": {"en": {"percent": 57.0, "official": "True"}, "chk": {"percent": 30.0, "official": "False"}, "pon": {"percent": 23.0, "official": "False"}, "kos": {"percent": 7.8, "official": "False"}, "yap": {"percent": 6.4, "official": "False"}, "uli": {"percent": 2.9, "official": "False"}}, "FO": {"fo": {"percent": 95.0, "official": "True"}}, "FR": {"fr": {"percent": 99.0, "official": "True"}, "en": {"percent": 39.0, "official": "False"}, "es": {"percent": 13.0, "official": "False"}, "de": {"percent": 5.0, "official": "False"}, "oc": {"percent": 3.0, "official": "False"}, "it": {"percent": 1.7, "official": "False"}, "pt": {"percent": 1.3, "official": "False"}, "pcd": {"percent": 1.1, "official": "False"}, "gsw": {"percent": 0.91, "official": "False"}, "br": {"percent": 0.83, "official": "False"}, "co": {"percent": 0.24, "official": "False"}, "ca": {"percent": 0.17, "official": "False"}, "nl": {"percent": 0.13, "official": "False"}, "eu": {"percent": 0.13, "official": "False"}, "frp": {"percent": 0.094, "official": "False"}, "ia": {"percent": 0.0002, "official": "False"}}, "GA": {"fr": {"percent": 63.0, "official": "True"}, "puu": {"percent": 9.0, "official": "False"}}, "GB": {"en": {"percent": 99.0, "official": "True"}, "fr": {"percent": 19.0, "official": "False"}, "de": {"percent": 6.0, "official": "False"}, "sco": {"percent": 2.7, "official": "False"}, "pa": {"percent": 0.79, "official": "False"}, "cy": {"percent": 0.77, "official": "True"}, "bn": {"percent": 0.67, "official": "False"}, "zh_Hant": {"percent": 0.54, "official": "False"}, "syl": {"percent": 0.51, "official": "False"}, "el": {"percent": 0.33, "official": "False"}, "it": {"percent": 0.33, "official": "False"}, "ks": {"percent": 0.19, "official": "False"}, "gd": {"percent": 0.099, "official": "True"}, "yi": {"percent": 0.049, "official": "False"}, "ml": {"percent": 0.035, "official": "False"}, "ga": {"percent": 0.026, "official": "True"}, "kw": {"percent": 0.003, "official": "False"}}, "GD": {"en": {"percent": 96.0, "official": "True"}}, "GE": {"ka": {"percent": 86.0, "official": "True"}, "xmf": {"percent": 11.0, "official": "False"}, "ru": {"percent": 9.0, "official": "False"}, "hy": {"percent": 7.0, "official": "False"}, "ab": {"percent": 2.2, "official": "True"}, "os": {"percent": 2.2, "official": "True"}, "ku": {"percent": 0.89, "official": "False"}}, "GF": {"fr": {"percent": 77.0, "official": "True"}, "gcr": {"percent": 26.0, "official": "False"}, "zh_Hant": {"percent": 2.5, "official": "False"}}, "GG": {"en": {"percent": 100.0, "official": "True"}}, "GH": {"ak": {"percent": 39.0, "official": "True"}, "en": {"percent": 21.0, "official": "True"}, "ee": {"percent": 11.0, "official": "True"}, "abr": {"percent": 5.0, "official": "False"}, "gur": {"percent": 3.5, "official": "False"}, "ada": {"percent": 3.0, "official": "False"}, "gaa": {"percent": 2.8, "official": "True"}, "nzi": {"percent": 1.0, "official": "False"}, "ha": {"percent": 0.86, "official": "False"}, "saf": {"percent": 0.014, "official": "False"}, "ff": {"percent": 0.0, "official": "False"}, "ff_Adlm": {"percent": 0.0, "official": "False"}}, "GI": {"en": {"percent": 80.0, "official": "True"}, "es": {"percent": 50.0, "official": "False"}}, "GL": {"kl": {"percent": 84.0, "official": "True"}, "da": {"percent": 14.0, "official": "False"}}, "GM": {"en": {"percent": 40.0, "official": "True"}, "man": {"percent": 29.0, "official": "False"}, "ff": {"percent": 0.0, "official": "False"}, "ff_Adlm": {"percent": 0.0, "official": "False"}}, "GN": {"fr": {"percent": 29.0, "official": "True"}, "ff": {"percent": 26.0, "official": "False"}, "man_Nkoo": {"percent": 23.0, "official": "False"}, "sus": {"percent": 11.0, "official": "False"}, "nqo": {"percent": 5.0, "official": "False"}, "kpe": {"percent": 3.8, "official": "False"}, "ff_Adlm": {"percent": 0.0, "official": "False"}}, "GP": {"fr": {"percent": 90.0, "official": "True"}}, "GQ": {"es": {"percent": 87.0, "official": "True"}, "fan": {"percent": 51.0, "official": "False"}, "fr": {"percent": 8.8, "official": "True"}, "bvb": {"percent": 7.9, "official": "False"}, "pt": {"percent": 0.0001, "official": "True"}}, "GR": {"el": {"percent": 99.0, "official": "True"}, "en": {"percent": 51.0, "official": "False"}, "fr": {"percent": 9.0, "official": "False"}, "de": {"percent": 5.0, "official": "False"}, "pnt": {"percent": 3.7, "official": "False"}, "mk": {"percent": 1.6, "official": "False"}, "tr": {"percent": 1.2, "official": "False"}, "bg": {"percent": 0.27, "official": "False"}, "sq": {"percent": 0.094, "official": "False"}, "tsd": {"percent": 0.0019, "official": "False"}}, "GS": {"und": {"percent": 100.0, "official": "False"}}, "GT": {"es": {"percent": 93.0, "official": "True"}, "quc": {"percent": 7.0, "official": "True"}}, "GU": {"en": {"percent": 91.0, "official": "True"}, "ch": {"percent": 22.0, "official": "True"}}, "GW": {"pt": {"percent": 100.0, "official": "True"}, "knf": {"percent": 2.6, "official": "False"}, "ff": {"percent": 0.0001, "official": "False"}, "ff_Adlm": {"percent": 0.0001, "official": "False"}}, "GY": {"en": {"percent": 100.0, "official": "True"}}, "HK": {"zh_Hant": {"percent": 95.0, "official": "True"}, "yue": {"percent": 90.0, "official": "False"}, "en": {"percent": 51.0, "official": "True"}, "zh": {"percent": 5.0, "official": "False"}}, "HM": {"und": {"percent": 100.0, "official": "False"}}, "HN": {"es": {"percent": 78.0, "official": "True"}, "en": {"percent": 0.44, "official": "False"}}, "HR": {"hr": {"percent": 99.0, "official": "True"}, "en": {"percent": 49.0, "official": "False"}, "it": {"percent": 1.6, "official": "True"}}, "HT": {"ht": {"percent": 81.0, "official": "True"}, "fr": {"percent": 4.7, "official": "True"}}, "HU": {"hu": {"percent": 100.0, "official": "True"}, "en": {"percent": 20.0, "official": "False"}, "de": {"percent": 18.0, "official": "False"}, "fr": {"percent": 3.0, "official": "False"}, "ro": {"percent": 0.99, "official": "False"}, "hr": {"percent": 0.32, "official": "False"}, "sk": {"percent": 0.12, "official": "False"}, "sl": {"percent": 0.051, "official": "False"}}, "IC": {"es": {"percent": 98.0, "official": "True"}}, "ID": {"id": {"percent": 64.0, "official": "True"}, "jv": {"percent": 34.0, "official": "False"}, "su": {"percent": 12.0, "official": "False"}, "mad": {"percent": 6.3, "official": "False"}, "ms": {"percent": 3.4, "official": "False"}, "min": {"percent": 3.0, "official": "False"}, "bew": {"percent": 2.1, "official": "False"}, "ban": {"percent": 1.8, "official": "False"}, "bug": {"percent": 1.6, "official": "False"}, "bjn": {"percent": 1.5, "official": "False"}, "ace": {"percent": 1.4, "official": "False"}, "ms_Arab": {"percent": 1.2, "official": "False"}, "sas": {"percent": 0.97, "official": "False"}, "bbc": {"percent": 0.92, "official": "False"}, "zh_Hant": {"percent": 0.92, "official": "False"}, "mak": {"percent": 0.73, "official": "False"}, "ljp": {"percent": 0.69, "official": "False"}, "rej": {"percent": 0.46, "official": "False"}, "gor": {"percent": 0.41, "official": "False"}, "nij": {"percent": 0.37, "official": "False"}, "kge": {"percent": 0.32, "official": "False"}, "aoz": {"percent": 0.27, "official": "False"}, "kvr": {"percent": 0.14, "official": "False"}, "lbw": {"percent": 0.13, "official": "False"}, "gay": {"percent": 0.12, "official": "False"}, "rob": {"percent": 0.11, "official": "False"}, "mdr": {"percent": 0.092, "official": "False"}, "sxn": {"percent": 0.092, "official": "False"}, "sly": {"percent": 0.054, "official": "False"}, "mwv": {"percent": 0.024, "official": "False"}}, "IE": {"en": {"percent": 98.0, "official": "True"}, "ga": {"percent": 22.0, "official": "True"}, "fr": {"percent": 17.0, "official": "False"}}, "IL": {"he": {"percent": 100.0, "official": "True"}, "en": {"percent": 85.0, "official": "False"}, "ar": {"percent": 20.0, "official": "True"}, "ru": {"percent": 11.0, "official": "False"}, "ro": {"percent": 3.7, "official": "False"}, "yi": {"percent": 3.0, "official": "False"}, "pl": {"percent": 1.5, "official": "False"}, "lad": {"percent": 1.3, "official": "False"}, "hu": {"percent": 1.0, "official": "False"}, "am": {"percent": 0.59, "official": "False"}, "ti": {"percent": 0.12, "official": "False"}, "ml": {"percent": 0.092, "official": "False"}}, "IM": {"en": {"percent": 100.0, "official": "True"}, "gv": {"percent": 1.9, "official": "True"}}, "IN": {"hi": {"percent": 41.0, "official": "True"}, "en": {"percent": 19.0, "official": "True"}, "bn": {"percent": 8.1, "official": "True"}, "te": {"percent": 7.2, "official": "True"}, "mr": {"percent": 7.0, "official": "True"}, "ta": {"percent": 5.9, "official": "True"}, "ur": {"percent": 5.0, "official": "True"}, "gu": {"percent": 4.5, "official": "True"}, "kn": {"percent": 3.7, "official": "True"}, "ml": {"percent": 3.2, "official": "True"}, "or": {"percent": 3.2, "official": "True"}, "pa": {"percent": 2.8, "official": "True"}, "bho": {"percent": 2.3, "official": "False"}, "awa": {"percent": 1.9, "official": "False"}, "as": {"percent": 1.3, "official": "True"}, "bgc": {"percent": 1.2, "official": "False"}, "mag": {"percent": 1.2, "official": "False"}, "mwr": {"percent": 1.2, "official": "False"}, "mai": {"percent": 1.2, "official": "True"}, "hne": {"percent": 1.1, "official": "False"}, "dcc": {"percent": 0.99, "official": "False"}, "bjj": {"percent": 0.56, "official": "False"}, "ne": {"percent": 0.56, "official": "True"}, "sat": {"percent": 0.55, "official": "True"}, "wtm": {"percent": 0.46, "official": "False"}, "rkt": {"percent": 0.43, "official": "False"}, "ks": {"percent": 0.41, "official": "True"}, "kok": {"percent": 0.37, "official": "True"}, "gom": {"percent": 0.32, "official": "False"}, "swv": {"percent": 0.28, "official": "False"}, "gbm": {"percent": 0.27, "official": "False"}, "lmn": {"percent": 0.27, "official": "False"}, "sd": {"percent": 0.26, "official": "True"}, "gon": {"percent": 0.24, "official": "False"}, "kfy": {"percent": 0.22, "official": "False"}, "doi": {"percent": 0.2, "official": "False"}, "kru": {"percent": 0.19, "official": "False"}, "sck": {"percent": 0.18, "official": "False"}, "wbq": {"percent": 0.18, "official": "False"}, "xnr": {"percent": 0.16, "official": "False"}, "tcy": {"percent": 0.15, "official": "False"}, "wbr": {"percent": 0.15, "official": "False"}, "khn": {"percent": 0.15, "official": "False"}, "brx": {"percent": 0.14, "official": "False"}, "noe": {"percent": 0.13, "official": "False"}, "bhb": {"percent": 0.12, "official": "False"}, "mni": {"percent": 0.11, "official": "False"}, "raj": {"percent": 0.1, "official": "False"}, "hi_Latn": {"percent": 0.1, "official": "False"}, "hoc": {"percent": 0.099, "official": "False"}, "mtr": {"percent": 0.097, "official": "False"}, "unr": {"percent": 0.094, "official": "False"}, "bhi": {"percent": 0.092, "official": "False"}, "hoj": {"percent": 0.082, "official": "False"}, "kha": {"percent": 0.08, "official": "True"}, "kfr": {"percent": 0.075, "official": "False"}, "grt": {"percent": 0.053, "official": "False"}, "unx": {"percent": 0.048, "official": "False"}, "bfy": {"percent": 0.037, "official": "False"}, "srx": {"percent": 0.035, "official": "False"}, "saz": {"percent": 0.029, "official": "False"}, "ccp": {"percent": 0.028, "official": "False"}, "sd_Deva": {"percent": 0.026, "official": "True"}, "bfq": {"percent": 0.023, "official": "False"}, "njo": {"percent": 0.023, "official": "False"}, "ria": {"percent": 0.013, "official": "False"}, "bo": {"percent": 0.011, "official": "False"}, "bpy": {"percent": 0.0068, "official": "False"}, "bft": {"percent": 0.0062, "official": "False"}, "bra": {"percent": 0.0041, "official": "False"}, "lep": {"percent": 0.0035, "official": "False"}, "btv": {"percent": 0.0026, "official": "False"}, "lif": {"percent": 0.0026, "official": "False"}, "lah": {"percent": 0.0025, "official": "False"}, "sa": {"percent": 0.0012, "official": "True"}, "kht": {"percent": 0.0007, "official": "False"}, "dv": {"percent": 0.0003, "official": "False"}, "dz": {"percent": 0.0002, "official": "False"}}, "IO": {"en": {"percent": 100.0, "official": "True"}}, "IQ": {"ar": {"percent": 68.0, "official": "True"}, "en": {"percent": 35.0, "official": "False"}, "ckb": {"percent": 20.0, "official": "True"}, "az_Arab": {"percent": 1.8, "official": "True"}, "fa": {"percent": 0.87, "official": "False"}, "lrc": {"percent": 0.61, "official": "False"}, "syr": {"percent": 0.5, "official": "False"}}, "IR": {"fa": {"percent": 75.0, "official": "True"}, "az_Arab": {"percent": 24.0, "official": "False"}, "mzn": {"percent": 5.0, "official": "False"}, "glk": {"percent": 4.6, "official": "False"}, "ckb": {"percent": 3.9, "official": "False"}, "sdh": {"percent": 3.7, "official": "False"}, "tk": {"percent": 2.8, "official": "False"}, "lrc": {"percent": 2.1, "official": "False"}, "ar": {"percent": 2.0, "official": "False"}, "bal": {"percent": 2.0, "official": "False"}, "rmt": {"percent": 1.9, "official": "False"}, "bqi": {"percent": 1.4, "official": "False"}, "luz": {"percent": 1.2, "official": "False"}, "lki": {"percent": 0.76, "official": "False"}, "bgn": {"percent": 0.56, "official": "False"}, "prd": {"percent": 0.5, "official": "False"}, "hy": {"percent": 0.24, "official": "False"}, "ps": {"percent": 0.16, "official": "False"}, "ka": {"percent": 0.071, "official": "False"}, "gbz": {"percent": 0.0094, "official": "False"}, "kk_Arab": {"percent": 0.0035, "official": "False"}}, "IS": {"is": {"percent": 100.0, "official": "True"}, "da": {"percent": 0.64, "official": "False"}}, "IT": {"it": {"percent": 95.0, "official": "True"}, "en": {"percent": 34.0, "official": "False"}, "fr": {"percent": 6.3, "official": "True"}, "sc": {"percent": 1.7, "official": "False"}, "de": {"percent": 1.6, "official": "False"}, "vec": {"percent": 1.3, "official": "False"}, "nap": {"percent": 0.97, "official": "False"}, "lij": {"percent": 0.86, "official": "False"}, "scn": {"percent": 0.82, "official": "False"}, "sl": {"percent": 0.17, "official": "False"}, "sdc": {"percent": 0.17, "official": "False"}, "fur": {"percent": 0.06, "official": "False"}, "egl": {"percent": 0.05, "official": "False"}, "ca": {"percent": 0.035, "official": "False"}, "el": {"percent": 0.035, "official": "False"}, "lmo": {"percent": 0.03, "official": "False"}, "pms": {"percent": 0.0099, "official": "False"}, "hr": {"percent": 0.0056, "official": "False"}, "rgn": {"percent": 0.0, "official": "False"}}, "JE": {"en": {"percent": 95.0, "official": "True"}}, "JM": {"en": {"percent": 98.0, "official": "True"}, "jam": {"percent": 95.0, "official": "False"}}, "JO": {"ar": {"percent": 100.0, "official": "True"}, "en": {"percent": 45.0, "official": "False"}}, "JP": {"ja": {"percent": 95.0, "official": "True"}, "ryu": {"percent": 0.77, "official": "False"}, "ko": {"percent": 0.52, "official": "False"}}, "KE": {"sw": {"percent": 66.0, "official": "True"}, "en": {"percent": 19.0, "official": "True"}, "ki": {"percent": 17.0, "official": "False"}, "luy": {"percent": 11.0, "official": "False"}, "luo": {"percent": 9.8, "official": "False"}, "kam": {"percent": 7.6, "official": "False"}, "kln": {"percent": 7.6, "official": "False"}, "guz": {"percent": 4.9, "official": "False"}, "mer": {"percent": 4.0, "official": "False"}, "mas": {"percent": 1.6, "official": "False"}, "ebu": {"percent": 1.5, "official": "False"}, "so": {"percent": 1.3, "official": "False"}, "dav": {"percent": 0.82, "official": "False"}, "teo": {"percent": 0.74, "official": "False"}, "pko": {"percent": 0.69, "official": "False"}, "om": {"percent": 0.47, "official": "False"}, "saq": {"percent": 0.46, "official": "False"}, "ar": {"percent": 0.046, "official": "False"}, "pa": {"percent": 0.019, "official": "False"}, "gu": {"percent": 0.0093, "official": "False"}}, "KG": {"ky": {"percent": 48.0, "official": "True"}, "ru": {"percent": 36.0, "official": "True"}}, "KH": {"km": {"percent": 89.0, "official": "True"}, "cja": {"percent": 1.6, "official": "False"}, "kdt": {"percent": 0.11, "official": "False"}}, "KI": {"en": {"percent": 100.0, "official": "True"}, "gil": {"percent": 60.0, "official": "True"}}, "KM": {"ar": {"percent": 66.0, "official": "True"}, "fr": {"percent": 56.0, "official": "True"}, "zdj": {"percent": 37.0, "official": "True"}, "wni": {"percent": 34.0, "official": "True"}}, "KN": {"en": {"percent": 98.0, "official": "True"}}, "KP": {"ko": {"percent": 88.0, "official": "True"}}, "KR": {"ko": {"percent": 100.0, "official": "True"}}, "KW": {"ar": {"percent": 100.0, "official": "True"}}, "KY": {"en": {"percent": 98.0, "official": "True"}}, "KZ": {"ru": {"percent": 72.0, "official": "True"}, "kk": {"percent": 64.0, "official": "True"}, "en": {"percent": 15.0, "official": "False"}, "de": {"percent": 6.4, "official": "False"}, "ug_Cyrl": {"percent": 2.0, "official": "False"}}, "LA": {"lo": {"percent": 69.0, "official": "True"}, "kjg": {"percent": 5.8, "official": "False"}, "kdt": {"percent": 0.96, "official": "False"}}, "LB": {"ar": {"percent": 86.0, "official": "True"}, "en": {"percent": 40.0, "official": "False"}, "hy": {"percent": 5.2, "official": "False"}, "ku_Arab": {"percent": 1.7, "official": "False"}, "fr": {"percent": 0.37, "official": "False"}}, "LC": {"en": {"percent": 90.0, "official": "True"}}, "LI": {"de": {"percent": 100.0, "official": "True"}, "gsw": {"percent": 85.0, "official": "True"}, "wae": {"percent": 3.3, "official": "False"}}, "LK": {"si": {"percent": 68.0, "official": "True"}, "ta": {"percent": 15.0, "official": "True"}, "en": {"percent": 10.0, "official": "False"}}, "LR": {"en": {"percent": 83.0, "official": "True"}, "kpe": {"percent": 14.0, "official": "False"}, "vai": {"percent": 2.6, "official": "False"}, "men": {"percent": 0.48, "official": "False"}, "ff": {"percent": 0.0, "official": "False"}, "ff_Adlm": {"percent": 0.0, "official": "False"}, "vai_Latn": {"percent": 0.0, "official": "False"}}, "LS": {"st": {"percent": 98.0, "official": "True"}, "en": {"percent": 27.0, "official": "True"}, "zu": {"percent": 14.0, "official": "False"}, "ss": {"percent": 2.4, "official": "False"}, "xh": {"percent": 0.99, "official": "False"}}, "LT": {"lt": {"percent": 86.0, "official": "True"}, "ru": {"percent": 80.0, "official": "False"}, "en": {"percent": 38.0, "official": "False"}, "de": {"percent": 14.0, "official": "False"}, "sgs": {"percent": 0.0, "official": "False"}}, "LU": {"fr": {"percent": 87.0, "official": "True"}, "lb": {"percent": 67.0, "official": "True"}, "de": {"percent": 63.0, "official": "True"}, "en": {"percent": 56.0, "official": "False"}, "pt": {"percent": 16.0, "official": "False"}}, "LV": {"lv": {"percent": 61.0, "official": "True"}, "en": {"percent": 46.0, "official": "False"}, "ru": {"percent": 38.0, "official": "False"}, "ltg": {"percent": 8.9, "official": "False"}}, "LY": {"ar": {"percent": 74.0, "official": "True"}}, "MA": {"ary": {"percent": 87.0, "official": "False"}, "ar": {"percent": 62.0, "official": "True"}, "zgh": {"percent": 22.0, "official": "False"}, "fr": {"percent": 20.0, "official": "True"}, "en": {"percent": 14.0, "official": "False"}, "tzm": {"percent": 9.8, "official": "True"}, "shi": {"percent": 8.7, "official": "False"}, "shi_Latn": {"percent": 8.7, "official": "False"}, "rif": {"percent": 4.9, "official": "False"}, "rif_Latn": {"percent": 4.9, "official": "False"}, "es": {"percent": 0.065, "official": "False"}}, "MC": {"fr": {"percent": 99.0, "official": "True"}}, "MD": {"ro": {"percent": 63.0, "official": "True"}, "uk": {"percent": 14.0, "official": "False"}, "bg": {"percent": 9.4, "official": "False"}, "gag": {"percent": 3.3, "official": "False"}, "ru": {"percent": 3.0, "official": "False"}}, "ME": {"sr_Latn": {"percent": 100.0, "official": "True"}, "sq": {"percent": 7.9, "official": "False"}, "sr": {"percent": 5.0, "official": "False"}}, "MF": {"fr": {"percent": 100.0, "official": "True"}}, "MG": {"mg": {"percent": 90.0, "official": "True"}, "fr": {"percent": 69.0, "official": "True"}, "en": {"percent": 18.0, "official": "True"}}, "MH": {"en": {"percent": 93.0, "official": "True"}, "mh": {"percent": 73.0, "official": "True"}}, "MK": {"mk": {"percent": 67.0, "official": "True"}, "sq": {"percent": 25.0, "official": "True"}, "tr": {"percent": 3.5, "official": "False"}}, "ML": {"bm": {"percent": 46.0, "official": "False"}, "fr": {"percent": 46.0, "official": "True"}, "ffm": {"percent": 7.7, "official": "False"}, "snk": {"percent": 5.9, "official": "False"}, "mwk": {"percent": 5.0, "official": "False"}, "ses": {"percent": 3.4, "official": "False"}, "tmh": {"percent": 2.1, "official": "False"}, "bm_Nkoo": {"percent": 2.0, "official": "False"}, "khq": {"percent": 1.7, "official": "False"}, "dtm": {"percent": 1.1, "official": "False"}, "kao": {"percent": 1.0, "official": "False"}, "ar": {"percent": 0.9, "official": "False"}, "bmq": {"percent": 0.86, "official": "False"}, "bze": {"percent": 0.85, "official": "False"}}, "MM": {"my": {"percent": 64.0, "official": "True"}, "shn": {"percent": 6.4, "official": "False"}, "kac": {"percent": 1.7, "official": "False"}, "rhg": {"percent": 1.7, "official": "False"}, "mnw": {"percent": 1.5, "official": "False"}, "kht": {"percent": 0.0075, "official": "False"}}, "MN": {"mn": {"percent": 93.0, "official": "True"}, "kk_Arab": {"percent": 7.2, "official": "False"}, "zh": {"percent": 1.4, "official": "False"}, "ru": {"percent": 0.13, "official": "False"}, "ug_Cyrl": {"percent": 0.032, "official": "False"}}, "MO": {"zh_Hant": {"percent": 98.0, "official": "True"}, "pt": {"percent": 5.0, "official": "True"}, "zh": {"percent": 5.0, "official": "False"}, "en": {"percent": 2.3, "official": "False"}}, "MP": {"en": {"percent": 97.0, "official": "True"}, "ch": {"percent": 18.0, "official": "False"}}, "MQ": {"fr": {"percent": 98.0, "official": "True"}}, "MR": {"ar": {"percent": 85.0, "official": "True"}, "fr": {"percent": 17.0, "official": "False"}, "ff": {"percent": 5.7, "official": "False"}, "wo": {"percent": 0.25, "official": "False"}, "ff_Adlm": {"percent": 0.0, "official": "False"}}, "MS": {"en": {"percent": 65.0, "official": "True"}}, "MT": {"mt": {"percent": 100.0, "official": "True"}, "en": {"percent": 88.0, "official": "True"}, "it": {"percent": 56.0, "official": "False"}, "fr": {"percent": 11.0, "official": "False"}}, "MU": {"mfe": {"percent": 90.0, "official": "False"}, "en": {"percent": 72.0, "official": "True"}, "bho": {"percent": 27.0, "official": "False"}, "ur": {"percent": 5.2, "official": "False"}, "fr": {"percent": 3.0, "official": "True"}, "ta": {"percent": 2.5, "official": "False"}}, "MV": {"dv": {"percent": 94.0, "official": "True"}}, "MW": {"en": {"percent": 63.0, "official": "True"}, "ny": {"percent": 63.0, "official": "True"}, "tum": {"percent": 8.4, "official": "False"}, "tog": {"percent": 0.98, "official": "False"}, "zu": {"percent": 0.33, "official": "False"}}, "MX": {"es": {"percent": 83.0, "official": "True"}, "en": {"percent": 13.0, "official": "False"}, "yua": {"percent": 0.67, "official": "False"}, "nhe": {"percent": 0.39, "official": "False"}, "nhw": {"percent": 0.39, "official": "False"}, "maz": {"percent": 0.34, "official": "False"}, "nch": {"percent": 0.19, "official": "False"}, "sei": {"percent": 0.0007, "official": "False"}}, "MY": {"ms": {"percent": 75.0, "official": "True"}, "en": {"percent": 21.0, "official": "False"}, "zh": {"percent": 17.0, "official": "False"}, "ta": {"percent": 4.2, "official": "False"}, "iba": {"percent": 2.5, "official": "False"}, "jv": {"percent": 1.2, "official": "False"}, "zmi": {"percent": 1.2, "official": "False"}, "dtp": {"percent": 0.56, "official": "False"}, "ml": {"percent": 0.15, "official": "False"}, "bug": {"percent": 0.079, "official": "False"}, "bjn": {"percent": 0.015, "official": "False"}}, "MZ": {"pt": {"percent": 27.0, "official": "True"}, "vmw": {"percent": 13.0, "official": "False"}, "ndc": {"percent": 9.9, "official": "False"}, "ts": {"percent": 7.9, "official": "False"}, "ngl": {"percent": 6.8, "official": "False"}, "seh": {"percent": 4.6, "official": "False"}, "mgh": {"percent": 4.5, "official": "False"}, "rng": {"percent": 3.4, "official": "False"}, "ny": {"percent": 2.6, "official": "False"}, "yao": {"percent": 2.4, "official": "False"}, "sw": {"percent": 0.031, "official": "False"}, "zu": {"percent": 0.006, "official": "False"}}, "NA": {"af": {"percent": 75.0, "official": "False"}, "kj": {"percent": 35.0, "official": "False"}, "ng": {"percent": 21.0, "official": "False"}, "naq": {"percent": 11.0, "official": "False"}, "hz": {"percent": 9.1, "official": "False"}, "en": {"percent": 7.0, "official": "True"}, "de": {"percent": 0.9, "official": "False"}, "tn": {"percent": 0.56, "official": "False"}}, "NC": {"fr": {"percent": 96.0, "official": "True"}}, "NE": {"ha": {"percent": 41.0, "official": "False"}, "fr": {"percent": 29.0, "official": "True"}, "dje": {"percent": 17.0, "official": "False"}, "fuq": {"percent": 7.0, "official": "False"}, "tmh": {"percent": 6.0, "official": "False"}, "ar": {"percent": 0.21, "official": "False"}, "twq": {"percent": 0.035, "official": "False"}, "ff": {"percent": 0.0, "official": "False"}, "ff_Adlm": {"percent": 0.0, "official": "False"}}, "NF": {"en": {"percent": 96.0, "official": "True"}}, "NG": {"en": {"percent": 53.0, "official": "True"}, "pcm": {"percent": 21.0, "official": "False"}, "ha": {"percent": 13.0, "official": "False"}, "ig": {"percent": 13.0, "official": "False"}, "yo": {"percent": 13.0, "official": "True"}, "fuv": {"percent": 6.7, "official": "False"}, "tiv": {"percent": 1.6, "official": "False"}, "efi": {"percent": 1.4, "official": "False"}, "ibb": {"percent": 1.4, "official": "False"}, "ha_Arab": {"percent": 1.0, "official": "False"}, "bin": {"percent": 0.71, "official": "False"}, "kaj": {"percent": 0.21, "official": "False"}, "kcg": {"percent": 0.093, "official": "False"}, "ar": {"percent": 0.071, "official": "False"}, "cch": {"percent": 0.021, "official": "False"}, "amo": {"percent": 0.0087, "official": "False"}, "ff": {"percent": 0.0, "official": "False"}, "ff_Adlm": {"percent": 0.0, "official": "False"}}, "NI": {"es": {"percent": 78.0, "official": "True"}}, "NL": {"nl": {"percent": 100.0, "official": "True"}, "en": {"percent": 90.0, "official": "False"}, "de": {"percent": 71.0, "official": "False"}, "fr": {"percent": 29.0, "official": "False"}, "nds": {"percent": 11.0, "official": "False"}, "li": {"percent": 5.5, "official": "False"}, "fy": {"percent": 4.3, "official": "True"}, "gos": {"percent": 3.6, "official": "False"}, "id": {"percent": 1.8, "official": "False"}, "zea": {"percent": 1.4, "official": "False"}, "rif_Latn": {"percent": 1.2, "official": "False"}, "tr": {"percent": 1.2, "official": "False"}}, "NO": {"nb": {"percent": 100.0, "official": "True"}, "nn": {"percent": 25.0, "official": "True"}, "se": {"percent": 0.29, "official": "True"}}, "NP": {"ne": {"percent": 44.0, "official": "True"}, "mai": {"percent": 11.0, "official": "False"}, "bho": {"percent": 6.8, "official": "False"}, "new": {"percent": 3.3, "official": "False"}, "jml": {"percent": 3.2, "official": "False"}, "en": {"percent": 3.0, "official": "False"}, "dty": {"percent": 2.5, "official": "False"}, "awa": {"percent": 2.2, "official": "False"}, "thl": {"percent": 2.0, "official": "False"}, "bap": {"percent": 1.5, "official": "False"}, "tdg": {"percent": 1.3, "official": "False"}, "thr": {"percent": 1.2, "official": "False"}, "mgp": {"percent": 1.1, "official": "False"}, "lif": {"percent": 1.1, "official": "False"}, "thq": {"percent": 1.0, "official": "False"}, "mrd": {"percent": 0.83, "official": "False"}, "bfy": {"percent": 0.54, "official": "False"}, "xsr": {"percent": 0.52, "official": "False"}, "rjs": {"percent": 0.44, "official": "False"}, "taj": {"percent": 0.43, "official": "False"}, "hi": {"percent": 0.42, "official": "False"}, "gvr": {"percent": 0.29, "official": "False"}, "bo": {"percent": 0.24, "official": "False"}, "tkt": {"percent": 0.24, "official": "False"}, "tdh": {"percent": 0.12, "official": "False"}, "bn": {"percent": 0.094, "official": "False"}, "unr_Deva": {"percent": 0.019, "official": "False"}, "lep": {"percent": 0.0093, "official": "False"}}, "NR": {"en": {"percent": 85.0, "official": "True"}, "na": {"percent": 63.0, "official": "True"}}, "NU": {"en": {"percent": 56.0, "official": "True"}, "niu": {"percent": 56.0, "official": "True"}}, "NZ": {"en": {"percent": 98.0, "official": "True"}, "mi": {"percent": 2.8, "official": "True"}}, "OM": {"ar": {"percent": 81.0, "official": "True"}, "bal": {"percent": 4.9, "official": "False"}, "fa": {"percent": 0.94, "official": "False"}}, "PA": {"es": {"percent": 69.0, "official": "True"}, "en": {"percent": 14.0, "official": "False"}, "zh_Hant": {"percent": 0.15, "official": "False"}}, "PE": {"es": {"percent": 73.0, "official": "True"}, "qu": {"percent": 15.0, "official": "True"}, "ay": {"percent": 1.6, "official": "False"}}, "PF": {"fr": {"percent": 61.0, "official": "True"}, "ty": {"percent": 31.0, "official": "True"}, "zh_Hant": {"percent": 7.8, "official": "False"}}, "PG": {"tpi": {"percent": 71.0, "official": "True"}, "en": {"percent": 50.0, "official": "True"}, "ho": {"percent": 2.1, "official": "True"}}, "PH": {"en": {"percent": 64.0, "official": "True"}, "fil": {"percent": 60.0, "official": "True"}, "es": {"percent": 31.0, "official": "False"}, "ceb": {"percent": 24.0, "official": "True"}, "ilo": {"percent": 9.6, "official": "True"}, "hil": {"percent": 8.4, "official": "True"}, "bik": {"percent": 3.0, "official": "False"}, "war": {"percent": 2.9, "official": "True"}, "fbl": {"percent": 2.3, "official": "False"}, "pam": {"percent": 2.3, "official": "False"}, "pag": {"percent": 1.4, "official": "True"}, "mdh": {"percent": 1.2, "official": "True"}, "tsg": {"percent": 1.1, "official": "True"}, "zh_Hant": {"percent": 0.73, "official": "False"}, "cps": {"percent": 0.66, "official": "False"}, "krj": {"percent": 0.39, "official": "False"}, "bto": {"percent": 0.28, "official": "False"}, "hnn": {"percent": 0.016, "official": "False"}, "tbw": {"percent": 0.0092, "official": "False"}, "bku": {"percent": 0.0073, "official": "False"}}, "PK": {"ur": {"percent": 95.0, "official": "True"}, "pa_Arab": {"percent": 70.0, "official": "False"}, "en": {"percent": 50.0, "official": "True"}, "lah": {"percent": 40.0, "official": "False"}, "ps": {"percent": 15.0, "official": "False"}, "sd": {"percent": 12.0, "official": "False"}, "skr": {"percent": 9.1, "official": "False"}, "bal": {"percent": 3.7, "official": "False"}, "brh": {"percent": 1.3, "official": "False"}, "hno": {"percent": 1.2, "official": "False"}, "fa": {"percent": 0.66, "official": "False"}, "bgn": {"percent": 0.57, "official": "False"}, "hnd": {"percent": 0.41, "official": "False"}, "tg_Arab": {"percent": 0.33, "official": "False"}, "gju": {"percent": 0.2, "official": "False"}, "bft": {"percent": 0.18, "official": "False"}, "kvx": {"percent": 0.16, "official": "False"}, "khw": {"percent": 0.15, "official": "False"}, "mvy": {"percent": 0.14, "official": "False"}, "kxp": {"percent": 0.11, "official": "False"}, "gjk": {"percent": 0.11, "official": "False"}, "ks": {"percent": 0.069, "official": "False"}, "trw": {"percent": 0.053, "official": "False"}, "btv": {"percent": 0.019, "official": "False"}}, "PL": {"pl": {"percent": 96.0, "official": "True"}, "en": {"percent": 33.0, "official": "False"}, "de": {"percent": 19.0, "official": "True"}, "ru": {"percent": 18.0, "official": "False"}, "szl": {"percent": 1.3, "official": "False"}, "be": {"percent": 0.58, "official": "False"}, "uk": {"percent": 0.39, "official": "False"}, "csb": {"percent": 0.13, "official": "True"}, "sli": {"percent": 0.031, "official": "False"}, "lt": {"percent": 0.021, "official": "True"}}, "PM": {"fr": {"percent": 96.0, "official": "True"}, "en": {"percent": 3.5, "official": "False"}}, "PN": {"en": {"percent": 92.0, "official": "True"}}, "PR": {"es": {"percent": 87.0, "official": "True"}, "en": {"percent": 49.0, "official": "True"}}, "PS": {"ar": {"percent": 100.0, "official": "True"}}, "PT": {"pt": {"percent": 96.0, "official": "True"}, "en": {"percent": 27.0, "official": "False"}, "fr": {"percent": 15.0, "official": "False"}, "es": {"percent": 10.0, "official": "False"}, "gl": {"percent": 0.14, "official": "False"}}, "PW": {"pau": {"percent": 74.0, "official": "True"}, "en": {"percent": 8.7, "official": "True"}}, "PY": {"gn": {"percent": 80.0, "official": "True"}, "es": {"percent": 3.2, "official": "True"}, "de": {"percent": 2.9, "official": "False"}}, "QA": {"ar": {"percent": 89.0, "official": "True"}, "fa": {"percent": 11.0, "official": "False"}, "ml": {"percent": 0.27, "official": "False"}}, "RE": {"fr": {"percent": 89.0, "official": "True"}, "rcf": {"percent": 71.0, "official": "False"}, "ta": {"percent": 15.0, "official": "False"}}, "RO": {"ro": {"percent": 90.0, "official": "True"}, "en": {"percent": 31.0, "official": "False"}, "fr": {"percent": 17.0, "official": "False"}, "es": {"percent": 10.0, "official": "False"}, "hu": {"percent": 6.6, "official": "False"}, "de": {"percent": 0.21, "official": "False"}, "tr": {"percent": 0.13, "official": "False"}, "sr_Latn": {"percent": 0.12, "official": "False"}, "bg": {"percent": 0.032, "official": "False"}, "el": {"percent": 0.019, "official": "False"}, "pl": {"percent": 0.013, "official": "False"}}, "RS": {"sr": {"percent": 99.0, "official": "True"}, "sr_Latn": {"percent": 99.0, "official": "True"}, "sq": {"percent": 19.0, "official": "False"}, "hu": {"percent": 4.8, "official": "True"}, "ro": {"percent": 2.1, "official": "True"}, "hr": {"percent": 0.93, "official": "True"}, "sk": {"percent": 0.85, "official": "True"}, "uk": {"percent": 0.0, "official": "True"}}, "RU": {"ru": {"percent": 94.0, "official": "True"}, "tt": {"percent": 1.4, "official": "True"}, "ba": {"percent": 1.3, "official": "True"}, "cv": {"percent": 1.3, "official": "False"}, "hy": {"percent": 0.84, "official": "False"}, "ce": {"percent": 0.66, "official": "True"}, "av": {"percent": 0.39, "official": "True"}, "udm": {"percent": 0.38, "official": "True"}, "chm": {"percent": 0.37, "official": "False"}, "sah": {"percent": 0.32, "official": "True"}, "os": {"percent": 0.32, "official": "False"}, "kbd": {"percent": 0.31, "official": "True"}, "myv": {"percent": 0.31, "official": "True"}, "dar": {"percent": 0.26, "official": "False"}, "bua": {"percent": 0.22, "official": "False"}, "mdf": {"percent": 0.21, "official": "True"}, "kum": {"percent": 0.2, "official": "True"}, "kv": {"percent": 0.18, "official": "True"}, "lez": {"percent": 0.18, "official": "True"}, "krc": {"percent": 0.17, "official": "True"}, "inh": {"percent": 0.16, "official": "True"}, "tyv": {"percent": 0.13, "official": "True"}, "az_Cyrl": {"percent": 0.093, "official": "True"}, "ady": {"percent": 0.088, "official": "True"}, "krl": {"percent": 0.082, "official": "False"}, "lbe": {"percent": 0.078, "official": "True"}, "koi": {"percent": 0.045, "official": "True"}, "mrj": {"percent": 0.021, "official": "False"}, "alt": {"percent": 0.014, "official": "False"}, "fi": {"percent": 0.012, "official": "False"}, "sr_Latn": {"percent": 0.0035, "official": "False"}, "vep": {"percent": 0.0025, "official": "False"}, "mn": {"percent": 0.0015, "official": "False"}, "izh": {"percent": 0.0001, "official": "False"}, "vot": {"percent": 0.0, "official": "False"}, "cu": {"percent": 0.0, "official": "False"}}, "RW": {"rw": {"percent": 77.0, "official": "True"}, "en": {"percent": 15.0, "official": "True"}, "fr": {"percent": 0.018, "official": "True"}}, "SA": {"ar": {"percent": 100.0, "official": "True"}, "ars": {"percent": 3.0, "official": "False"}}, "SB": {"en": {"percent": 100.0, "official": "True"}, "rug": {"percent": 1.4, "official": "False"}}, "SC": {"crs": {"percent": 98.0, "official": "False"}, "fr": {"percent": 60.0, "official": "True"}, "en": {"percent": 38.0, "official": "True"}}, "SD": {"ar": {"percent": 61.0, "official": "True"}, "en": {"percent": 61.0, "official": "True"}, "bej": {"percent": 5.4, "official": "False"}, "fvr": {"percent": 2.7, "official": "False"}, "ha_Arab": {"percent": 1.8, "official": "False"}, "mls": {"percent": 0.99, "official": "False"}, "fia": {"percent": 0.83, "official": "False"}, "zag": {"percent": 0.51, "official": "False"}}, "SE": {"sv": {"percent": 95.0, "official": "True"}, "en": {"percent": 86.0, "official": "False"}, "fi": {"percent": 2.2, "official": "True"}, "fit": {"percent": 0.55, "official": "False"}, "se": {"percent": 0.33, "official": "False"}, "rmu": {"percent": 0.093, "official": "False"}, "yi": {"percent": 0.029, "official": "False"}, "smj": {"percent": 0.015, "official": "False"}, "sma": {"percent": 0.0029, "official": "False"}, "ia": {"percent": 0.0, "official": "False"}}, "SG": {"en": {"percent": 93.0, "official": "True"}, "zh": {"percent": 77.0, "official": "True"}, "ms": {"percent": 14.0, "official": "True"}, "ta": {"percent": 2.1, "official": "True"}, "ml": {"percent": 0.16, "official": "False"}, "pa": {"percent": 0.15, "official": "False"}}, "SH": {"en": {"percent": 69.0, "official": "True"}}, "SI": {"sl": {"percent": 87.0, "official": "True"}, "hr": {"percent": 61.0, "official": "False"}, "en": {"percent": 59.0, "official": "False"}, "de": {"percent": 42.0, "official": "False"}, "hu": {"percent": 0.44, "official": "False"}, "it": {"percent": 0.19, "official": "False"}}, "SJ": {"nb": {"percent": 51.0, "official": "True"}, "ru": {"percent": 41.0, "official": "False"}}, "SK": {"sk": {"percent": 90.0, "official": "True"}, "cs": {"percent": 47.0, "official": "False"}, "en": {"percent": 26.0, "official": "False"}, "de": {"percent": 22.0, "official": "False"}, "hu": {"percent": 11.0, "official": "False"}, "uk": {"percent": 1.9, "official": "False"}, "pl": {"percent": 0.93, "official": "False"}}, "SL": {"kri": {"percent": 95.0, "official": "False"}, "en": {"percent": 35.0, "official": "True"}, "men": {"percent": 27.0, "official": "False"}, "tem": {"percent": 26.0, "official": "False"}, "ff": {"percent": 0.0, "official": "False"}, "ff_Adlm": {"percent": 0.0, "official": "False"}}, "SM": {"it": {"percent": 89.0, "official": "True"}, "eo": {"percent": 0.88, "official": "False"}}, "SN": {"wo": {"percent": 70.0, "official": "True"}, "fr": {"percent": 39.0, "official": "True"}, "ff": {"percent": 21.0, "official": "True"}, "srr": {"percent": 11.0, "official": "True"}, "dyo": {"percent": 2.6, "official": "True"}, "sav": {"percent": 1.5, "official": "True"}, "mfv": {"percent": 0.77, "official": "True"}, "bjt": {"percent": 0.61, "official": "True"}, "snf": {"percent": 0.24, "official": "True"}, "knf": {"percent": 0.21, "official": "True"}, "bsc": {"percent": 0.097, "official": "True"}, "mey": {"percent": 0.046, "official": "True"}, "tnr": {"percent": 0.021, "official": "True"}, "ff_Adlm": {"percent": 0.0, "official": "False"}}, "SO": {"so": {"percent": 78.0, "official": "True"}, "ar": {"percent": 34.0, "official": "True"}, "sw": {"percent": 2.0, "official": "False"}, "om": {"percent": 0.42, "official": "False"}}, "SR": {"nl": {"percent": 90.0, "official": "True"}, "srn": {"percent": 68.0, "official": "False"}, "zh_Hant": {"percent": 1.1, "official": "False"}}, "SS": {"ar": {"percent": 27.0, "official": "False"}, "en": {"percent": 27.0, "official": "True"}, "nus": {"percent": 5.6, "official": "False"}}, "ST": {"pt": {"percent": 85.0, "official": "True"}}, "SV": {"es": {"percent": 89.0, "official": "True"}}, "SX": {"en": {"percent": 68.0, "official": "True"}, "es": {"percent": 11.0, "official": "False"}, "vic": {"percent": 7.1, "official": "False"}, "nl": {"percent": 3.6, "official": "True"}}, "SY": {"ar": {"percent": 80.0, "official": "True"}, "ku": {"percent": 8.0, "official": "False"}, "fr": {"percent": 5.9, "official": "True"}, "hy": {"percent": 1.8, "official": "False"}, "syr": {"percent": 0.084, "official": "False"}}, "SZ": {"en": {"percent": 80.0, "official": "True"}, "ss": {"percent": 58.0, "official": "True"}, "zu": {"percent": 6.8, "official": "False"}, "ts": {"percent": 1.7, "official": "False"}}, "TA": {"en": {"percent": 99.0, "official": "False"}}, "TC": {"en": {"percent": 98.0, "official": "True"}}, "TD": {"fr": {"percent": 26.0, "official": "True"}, "ar": {"percent": 17.0, "official": "True"}}, "TF": {"fr": {"percent": 100.0, "official": "False"}}, "TG": {"fr": {"percent": 61.0, "official": "True"}, "ee": {"percent": 17.0, "official": "False"}, "ife": {"percent": 1.3, "official": "False"}}, "TH": {"th": {"percent": 80.0, "official": "True"}, "en": {"percent": 27.0, "official": "False"}, "tts": {"percent": 24.0, "official": "False"}, "nod": {"percent": 9.6, "official": "False"}, "sou": {"percent": 8.0, "official": "False"}, "mfa": {"percent": 5.0, "official": "False"}, "zh_Hant": {"percent": 1.8, "official": "False"}, "kxm": {"percent": 1.7, "official": "False"}, "kdt": {"percent": 0.48, "official": "False"}, "mnw": {"percent": 0.17, "official": "False"}, "shn": {"percent": 0.096, "official": "False"}, "lcp": {"percent": 0.01, "official": "False"}, "lwl": {"percent": 0.01, "official": "False"}}, "TJ": {"tg": {"percent": 100.0, "official": "True"}, "ru": {"percent": 12.0, "official": "False"}, "fa": {"percent": 0.78, "official": "False"}, "ar": {"percent": 0.011, "official": "False"}}, "TK": {"en": {"percent": 78.0, "official": "True"}, "tkl": {"percent": 78.0, "official": "True"}}, "TL": {"pt": {"percent": 59.0, "official": "True"}, "tet": {"percent": 59.0, "official": "True"}}, "TM": {"tk": {"percent": 70.0, "official": "True"}, "ru": {"percent": 12.0, "official": "False"}, "uz": {"percent": 9.0, "official": "False"}, "ku": {"percent": 0.4, "official": "False"}}, "TN": {"aeb": {"percent": 90.0, "official": "False"}, "ar": {"percent": 90.0, "official": "True"}, "fr": {"percent": 74.0, "official": "True"}}, "TO": {"to": {"percent": 95.0, "official": "True"}, "en": {"percent": 28.0, "official": "True"}}, "TR": {"tr": {"percent": 93.0, "official": "True"}, "en": {"percent": 17.0, "official": "False"}, "ku": {"percent": 5.5, "official": "False"}, "zza": {"percent": 1.4, "official": "False"}, "kbd": {"percent": 0.77, "official": "False"}, "az": {"percent": 0.74, "official": "False"}, "az_Arab": {"percent": 0.65, "official": "False"}, "ar": {"percent": 0.56, "official": "False"}, "bgx": {"percent": 0.46, "official": "False"}, "bg": {"percent": 0.42, "official": "False"}, "ady": {"percent": 0.39, "official": "False"}, "kiu": {"percent": 0.19, "official": "False"}, "hy": {"percent": 0.056, "official": "False"}, "ka": {"percent": 0.056, "official": "False"}, "sr_Latn": {"percent": 0.028, "official": "False"}, "lzz": {"percent": 0.028, "official": "False"}, "sq": {"percent": 0.021, "official": "False"}, "ab": {"percent": 0.0049, "official": "False"}, "el": {"percent": 0.0049, "official": "False"}, "tru": {"percent": 0.0037, "official": "False"}, "uz": {"percent": 0.0024, "official": "False"}, "ky_Latn": {"percent": 0.0014, "official": "False"}, "kk": {"percent": 0.0007, "official": "False"}}, "TT": {"en": {"percent": 88.0, "official": "True"}, "es": {"percent": 0.34, "official": "False"}}, "TV": {"tvl": {"percent": 87.0, "official": "True"}, "en": {"percent": 9.4, "official": "True"}}, "TW": {"zh_Hant": {"percent": 95.0, "official": "True"}, "trv": {"percent": 0.02, "official": "False"}}, "TZ": {"sw": {"percent": 90.0, "official": "True"}, "en": {"percent": 69.0, "official": "True"}, "suk": {"percent": 8.7, "official": "False"}, "nym": {"percent": 3.3, "official": "False"}, "kde": {"percent": 2.5, "official": "False"}, "bez": {"percent": 1.7, "official": "False"}, "ksb": {"percent": 1.7, "official": "False"}, "mas": {"percent": 1.5, "official": "False"}, "mgy": {"percent": 1.4, "official": "False"}, "asa": {"percent": 1.2, "official": "False"}, "lag": {"percent": 0.87, "official": "False"}, "jmc": {"percent": 0.74, "official": "False"}, "rof": {"percent": 0.74, "official": "False"}, "vun": {"percent": 0.74, "official": "False"}, "rwk": {"percent": 0.22, "official": "False"}, "sbp": {"percent": 0.2, "official": "False"}}, "UA": {"uk": {"percent": 65.0, "official": "True"}, "ru": {"percent": 46.0, "official": "True"}, "pl": {"percent": 2.4, "official": "False"}, "yi": {"percent": 1.3, "official": "False"}, "rue": {"percent": 1.2, "official": "False"}, "be": {"percent": 0.83, "official": "False"}, "crh": {"percent": 0.56, "official": "False"}, "ro": {"percent": 0.52, "official": "False"}, "bg": {"percent": 0.49, "official": "False"}, "tr": {"percent": 0.42, "official": "False"}, "hu": {"percent": 0.37, "official": "False"}, "el": {"percent": 0.016, "official": "False"}}, "UG": {"sw": {"percent": 75.0, "official": "True"}, "lg": {"percent": 13.0, "official": "False"}, "nyn": {"percent": 6.3, "official": "False"}, "cgg": {"percent": 5.4, "official": "False"}, "xog": {"percent": 5.3, "official": "False"}, "en": {"percent": 3.9, "official": "True"}, "teo": {"percent": 3.9, "official": "False"}, "laj": {"percent": 3.8, "official": "False"}, "ach": {"percent": 3.7, "official": "False"}, "myx": {"percent": 2.9, "official": "False"}, "rw": {"percent": 2.1, "official": "False"}, "ttj": {"percent": 1.9, "official": "False"}, "hi": {"percent": 0.0051, "official": "False"}}, "UM": {"en": {"percent": 100.0, "official": "True"}}, "US": {"en": {"percent": 96.0, "official": "True"}, "es": {"percent": 9.6, "official": "True"}, "zh_Hant": {"percent": 0.69, "official": "False"}, "fr": {"percent": 0.56, "official": "False"}, "de": {"percent": 0.47, "official": "False"}, "fil": {"percent": 0.42, "official": "False"}, "it": {"percent": 0.34, "official": "False"}, "vi": {"percent": 0.34, "official": "False"}, "ko": {"percent": 0.3, "official": "False"}, "ru": {"percent": 0.24, "official": "False"}, "nv": {"percent": 0.05, "official": "False"}, "yi": {"percent": 0.049, "official": "False"}, "pdc": {"percent": 0.039, "official": "False"}, "haw": {"percent": 0.0089, "official": "True"}, "frc": {"percent": 0.0084, "official": "False"}, "chr": {"percent": 0.0077, "official": "False"}, "esu": {"percent": 0.0063, "official": "False"}, "dak": {"percent": 0.0059, "official": "False"}, "cho": {"percent": 0.0033, "official": "False"}, "lkt": {"percent": 0.0025, "official": "False"}, "ik": {"percent": 0.0024, "official": "False"}, "mus": {"percent": 0.0012, "official": "False"}, "cic": {"percent": 0.0, "official": "False"}, "cad": {"percent": 0.0, "official": "False"}, "osa": {"percent": 0.0, "official": "False"}}, "UY": {"es": {"percent": 88.0, "official": "True"}}, "UZ": {"uz": {"percent": 85.0, "official": "True"}, "uz_Cyrl": {"percent": 15.0, "official": "True"}, "ru": {"percent": 14.0, "official": "False"}, "kaa": {"percent": 1.6, "official": "False"}, "tr": {"percent": 0.76, "official": "False"}}, "VA": {"it": {"percent": 82.0, "official": "True"}, "la": {"percent": 82.0, "official": "False"}}, "VC": {"en": {"percent": 96.0, "official": "True"}}, "VE": {"es": {"percent": 82.0, "official": "True"}, "yrl": {"percent": 0.007, "official": "False"}}, "VG": {"en": {"percent": 98.0, "official": "True"}}, "VI": {"en": {"percent": 75.0, "official": "True"}}, "VN": {"vi": {"percent": 86.0, "official": "True"}, "zh_Hant": {"percent": 1.1, "official": "False"}, "cjm": {"percent": 0.089, "official": "False"}}, "VU": {"bi": {"percent": 90.0, "official": "True"}, "en": {"percent": 83.0, "official": "True"}, "fr": {"percent": 50.0, "official": "True"}}, "WF": {"wls": {"percent": 60.0, "official": "False"}, "fr": {"percent": 48.0, "official": "True"}, "fud": {"percent": 30.0, "official": "False"}}, "WS": {"sm": {"percent": 100.0, "official": "True"}, "en": {"percent": 2.1, "official": "True"}}, "XK": {"sq": {"percent": 92.0, "official": "True"}, "aln": {"percent": 74.0, "official": "False"}, "sr": {"percent": 5.0, "official": "True"}, "sr_Latn": {"percent": 5.0, "official": "True"}}, "YE": {"ar": {"percent": 74.0, "official": "True"}, "en": {"percent": 9.0, "official": "False"}}, "YT": {"swb": {"percent": 88.0, "official": "False"}, "fr": {"percent": 57.0, "official": "True"}, "buc": {"percent": 23.0, "official": "False"}, "sw": {"percent": 1.4, "official": "False"}}, "ZA": {"en": {"percent": 31.0, "official": "True"}, "zu": {"percent": 24.0, "official": "True"}, "xh": {"percent": 18.0, "official": "True"}, "af": {"percent": 13.0, "official": "True"}, "nso": {"percent": 9.4, "official": "True"}, "tn": {"percent": 8.2, "official": "True"}, "st": {"percent": 7.9, "official": "True"}, "ts": {"percent": 4.4, "official": "True"}, "ss": {"percent": 2.7, "official": "True"}, "ve": {"percent": 2.3, "official": "True"}, "hi": {"percent": 2.0, "official": "False"}, "nr": {"percent": 1.6, "official": "True"}, "sw": {"percent": 0.0018, "official": "False"}}, "ZM": {"bem": {"percent": 31.0, "official": "False"}, "en": {"percent": 16.0, "official": "True"}, "ny": {"percent": 15.0, "official": "False"}, "loz": {"percent": 6.0, "official": "False"}}, "ZW": {"sn": {"percent": 81.0, "official": "True"}, "en": {"percent": 42.0, "official": "True"}, "nd": {"percent": 12.0, "official": "True"}, "mxc": {"percent": 6.5, "official": "False"}, "ndc": {"percent": 6.1, "official": "False"}, "kck": {"percent": 5.3, "official": "False"}, "ny": {"percent": 1.9, "official": "False"}, "ve": {"percent": 0.64, "official": "False"}, "tn": {"percent": 0.22, "official": "False"}}, "ZZ": {}}